CamundaLibrary/CamundaLibrary.py
CamundaLibrary/CamundaResources.py
CamundaLibrary/__init__.py
robotframework_camunda-2.0.3.dist-info/LICENSE
robotframework_camunda-2.0.3.dist-info/METADATA
robotframework_camunda-2.0.3.dist-info/WHEEL
robotframework_camunda-2.0.3.dist-info/top_level.txt
robotframework_camunda-2.0.3.dist-info/RECORD
