Metadata-Version: 2.1
Name: robotframework-camunda
Version: 2.0.3
Summary: Keywords for camunda rest api, leading open source workflow engine.
Home-page: https://github.com/MarketSquare/robotframework-camunda
Author: Markus Stahl
Author-email: markus.i.sverige@googlemail.com
License: Apache License, Version 2.0
Platform: UNKNOWN
Classifier: Intended Audience :: Developers
Classifier: Natural Language :: English
Classifier: Programming Language :: Python :: 3
Classifier: Topic :: Software Development
Classifier: License :: OSI Approved :: Apache Software License
Classifier: Operating System :: OS Independent
Classifier: Development Status :: 5 - Production/Stable
Classifier: Framework :: Robot Framework
License-File: LICENSE
Requires-Dist: robotframework (>=3.2)
Requires-Dist: requests
Requires-Dist: frozendict
Requires-Dist: generic-camunda-client (>=7.15.0)
Requires-Dist: requests-toolbelt
Requires-Dist: url-normalize
